tablegpt/__about__.py
tablegpt/__init__.py
tablegpt/errors.py
tablegpt/safety.py
tablegpt/tools.py
tablegpt/translation.py
tablegpt/utils.py
tablegpt/agent/__init__.py
tablegpt/agent/data_analyzer.py
tablegpt/agent/output_parser.py
tablegpt/agent/file_reading/__init__.py
tablegpt/agent/file_reading/data_normalizer.py
tablegpt/retriever/__init__.py
tablegpt/retriever/compressor.py
tablegpt/retriever/loader.py
tablegpt_agent-0.2.27.data/data/share/ipykernel/profile/tablegpt/startup/00-pandas.py
tablegpt_agent-0.2.27.data/data/share/ipykernel/profile/tablegpt/startup/98-udfs.py
tablegpt_agent-0.2.27.data/data/share/ipykernel/profile/tablegpt/startup/99-cfont.py
tablegpt_agent-0.2.27.dist-info/METADATA
tablegpt_agent-0.2.27.dist-info/WHEEL
tablegpt_agent-0.2.27.dist-info/licenses/LICENSE
tablegpt_agent-0.2.27.dist-info/RECORD
