Metadata-Version: 2.4
Name: tablegpt-agent
Version: 0.2.27
Project-URL: Documentation, https://tablegpt.github.io/tablegpt-agent/
Project-URL: Issues, https://github.com/tablegpt/tablegpt-agent/issues
Project-URL: Source, https://github.com/tablegpt/tablegpt-agent
Author-email: Aofeng Su <saf@zjuici.com>, Chen Zhou <zc@zjuici.com>, Junbo Zhao <j.zhao@zju.edu.cn>, Junlin Zhou <jlzhou@zjuici.com>, Tao Zhang <zt@zjuici.com>, Xiang Li <xli@zjuici.com>
License: 
License-File: LICENSE
Classifier: Development Status :: 4 - Beta
Classifier: Programming Language :: Python
Classifier: Programming Language :: Python :: 3.9
Classifier: Programming Language :: Python :: 3.10
Classifier: Programming Language :: Python :: 3.11
Classifier: Programming Language :: Python :: 3.12
Classifier: Programming Language :: Python :: Implementation :: CPython
Classifier: Programming Language :: Python :: Implementation :: PyPy
Requires-Python: >=3.9
Requires-Dist: chardet<6.0.0,>=5.2.0
Requires-Dist: langchain-core<1.0.0,>=0.3.0
Requires-Dist: langgraph<1.0.0,>=0.0.68
Requires-Dist: pandas<3.0.0,>=2.2
Requires-Dist: pppybox>=0.0.17
Provides-Extra: local
Requires-Dist: matplotlib<4.0.0,>=3.8.4; extra == 'local'
Requires-Dist: mplfonts<1.0.0,>=0.0.8; extra == 'local'
Requires-Dist: numexpr>=2.8.4; extra == 'local'
Requires-Dist: odfpy; extra == 'local'
Requires-Dist: openpyxl<4.0.0,>=3.1.2; extra == 'local'
Requires-Dist: pandas<3.0.0,>=2.2; extra == 'local'
Requires-Dist: pppybox[local]; extra == 'local'
Requires-Dist: scikit-learn<2.0.0,>=1.0.0; extra == 'local'
Requires-Dist: scipy<2.0.0,>=1.13.0; extra == 'local'
Requires-Dist: seaborn<1.0.0,>=0.13.1; extra == 'local'
Requires-Dist: statsmodels<1.0.0,>=0.10.0; extra == 'local'
Requires-Dist: tabulate<1.0.0,>=0.9.0; extra == 'local'
Requires-Dist: xlrd>=2.0.1; extra == 'local'
